sendmyl.py
sendmyl-4.3.post1.dist-info/LICENSE
sendmyl-4.3.post1.dist-info/METADATA
sendmyl-4.3.post1.dist-info/WHEEL
sendmyl-4.3.post1.dist-info/entry_points.txt
sendmyl-4.3.post1.dist-info/top_level.txt
sendmyl-4.3.post1.dist-info/RECORD
