Metadata-Version: 2.1
Name: sendmyl
Version: 4.3.post1
Summary: Simple lib to send mail
Author-email: Philipp Schmitt <philipp@schmitt.co>
License: GNU GENERAL PUBLIC LICENSE
Project-URL: homepage, https://github.com/pschmitt/sendmyl
Project-URL: documentation, https://github.com/pschmitt/sendmyl/blob/HEAD/README.md
Project-URL: repository, https://github.com/pschmitt/sendmyl
Project-URL: issues, https://github.com/pschmitt/sendmyl/issues
Requires-Python: >=3.7
License-File: LICENSE
Requires-Dist: myl-discovery >=0.6.0.dev0
Requires-Dist: rich <14.0.0,>=13.0.0
Requires-Dist: rich-argparse <2.0.0,>=1.5.0
Provides-Extra: dev
Requires-Dist: black ; extra == 'dev'
Requires-Dist: pyinstaller ; extra == 'dev'
Requires-Dist: mypy ; extra == 'dev'
